MANIFEST.in
README.rst
requirements.txt
setup.py
walker/__init__.py
walker/check_status.py
walker/downloadermiddlewares.py
walker/pipelines.py
walker/redis_feed.py
walker/scheduler.py
walker/start_project.py
walker/stats_collectors.py
walker/user_agents.list
walker/spiders/__init__.py
walker/spiders/exception_process.py
walker/spiders/helper.py
walker/spiders/utils.py
walker/templates/project/scrapy.cfg
walker/templates/project/module/__init__.py
walker/templates/project/module/proxy.list
walker/templates/project/module/settings.py.tmpl
walker/templates/project/module/spiders/__init__.py
walker/templates/project/module/spiders/item_field.py
walker/templates/project/module/spiders/item_xpath.py
walker/templates/project/module/spiders/page_xpath.py
walker/templates/project/module/spiders/spiders.py
web_walker.egg-info/PKG-INFO
web_walker.egg-info/SOURCES.txt
web_walker.egg-info/dependency_links.txt
web_walker.egg-info/entry_points.txt
web_walker.egg-info/requires.txt
web_walker.egg-info/top_level.txt
web_walker.egg-info/zip-safe