Metadata-Version: 1.1
Name: web-walker
Version: 3.1.1
Summary: your can crawl web pages with litte settings. based on scrapy. 
Home-page: https://www.github.com/ShichaoMa/webWalker
Author: cn
Author-email: 308299269@qq.com
License: MIT
Keywords: crawl web spider scrapy
Platform: UNKNOWN
Classifier: License :: OSI Approved :: MIT License
Classifier: Programming Language :: Python
Classifier: Intended Audience :: Developers
Classifier: Operating System :: OS Independent
